MANIFEST.in
account_tax.xml
account_tax_code.xml
l10n_ar_chart.xml
l10n_ar_wizard.xml
setup.py
./__init__.py
./__openerp__.py
i18n/es.po
i18n/es_AR.po
i18n/l10n_ar.pot
i18n/nl.po
i18n/pt.po
i18n/pt_BR.po
i18n/sl.po
i18n/tr.po
i18n/zh_CN.po
images/config_chart_l10n_ar.jpeg
images/l10n_ar_chart.jpeg
openerp_l10n_ar.egg-info/PKG-INFO
openerp_l10n_ar.egg-info/SOURCES.txt
openerp_l10n_ar.egg-info/dependency_links.txt
openerp_l10n_ar.egg-info/requires.txt
openerp_l10n_ar.egg-info/top_level.txt
static/src/img/icon.png